Metadata-Version: 1.0
Name: en-writer-passive-voice
Version: 2.3.1.2.0.3
Summary: English multi-task CNN trained on OntoNotes. Assigns context-specific token vectors, POS tags, dependency parse and named entities.
Home-page: https://explosion.ai
Author: Explosion
Author-email: contact@explosion.ai
License: MIT
Platform: UNKNOWN
